treeverse/__init__.py
treeverse/cli.py
treeverse/code_loaders.py
treeverse/core.py
treeverse/models.py
treeverse-0.2.1.dist-info/LICENSE
treeverse-0.2.1.dist-info/METADATA
treeverse-0.2.1.dist-info/WHEEL
treeverse-0.2.1.dist-info/entry_points.txt
treeverse-0.2.1.dist-info/RECORD
