Metadata-Version: 2.1
Name: treeverse
Version: 0.2.1
Summary: A flexible tool for traversing, filtering, and processing file trees
Home-page: https://github.com/ryzhakar/treeverse
License: AGPL-3.0-or-later
Keywords: file-tree,traversal,processing,filtering,cli
Author: Arthur Ryzhak
Author-email: ryzhakar@gmail.com
Requires-Python: >=3.11,<4.0
Classifier: Development Status :: 3 - Alpha
Classifier: Intended Audience :: Developers
Classifier: License :: OSI Approved :: GNU Affero General Public License v3 or later (AGPLv3+)
Classifier: Programming Language :: Python :: 3
Classifier: Programming Language :: Python :: 3.11
Classifier: Programming Language :: Python :: 3.12
Classifier: Topic :: Software Development :: Libraries :: Python Modules
Classifier: Topic :: Utilities
Requires-Dist: chardet (>=5.2.0,<6.0.0)
Requires-Dist: importlib (>=1.0.4,<2.0.0)
Requires-Dist: pydantic (>=2.7.4,<3.0.0)
Requires-Dist: python-magic (>=0.4.27,<0.5.0)
Requires-Dist: pyyaml (>=6.0.1,<7.0.0)
Requires-Dist: typer (>=0.12.3,<0.13.0)
Project-URL: Documentation, https://github.com/ryzhakar/treeverse#readme
Project-URL: Repository, https://github.com/ryzhakar/treeverse
